snip/__init__.py
snip/__main__.py
snip/logger.py
snip/api/__init__.py
snip/api/account.py
snip/api/books.py
snip/api/exceptions.py
snip/api/request.py
snip/api/schemas.py
snip/api/snippets.py
snip/api/token.py
snip/snippets/__init__.py
snip/snippets/__main__.py
snip/snippets/array.py
snip/snippets/base.py
snip/snippets/factory.py
snip/snippets/image.py
snip/snippets/link.py
snip/snippets/text.py
snip/token/__init__.py
snip/token/__main__.py
snip/token/token.py
snip/token/storage/__init__.py
snip/token/storage/file_store.py
snip/token/storage/keyring_store.py
snip_python-0.3.1.dist-info/METADATA
snip_python-0.3.1.dist-info/WHEEL
snip_python-0.3.1.dist-info/entry_points.txt
snip_python-0.3.1.dist-info/RECORD
