Metadata-Version: 2.4
Name: snip-python
Version: 0.3.1
Summary: Python package to interface with Snip Lab Notebook 
Project-URL: Homepage, https://snip.roentgen.physik.uni-goettingen.de
Project-URL: Documentation, https://snip-python.readthedocs.io/
Project-URL: Repository, https://gitlab.gwdg.de/irp/snip
Author-email: "Sebastian B. Mohr" <sebastianbernd.mohr@uni-goettingen.de>
Classifier: Development Status :: 3 - Alpha
Classifier: Intended Audience :: Science/Research
Classifier: License :: OSI Approved :: GNU General Public License v3 (GPLv3)
Classifier: Operating System :: OS Independent
Classifier: Programming Language :: Python :: 3
Classifier: Programming Language :: Python :: 3.10
Classifier: Programming Language :: Python :: 3.11
Classifier: Programming Language :: Python :: 3.12
Classifier: Programming Language :: Python :: 3.13
Requires-Python: >=3.10
Requires-Dist: jsonschema>=4.23.0
Requires-Dist: keyring>=25.3.0
Requires-Dist: nest-asyncio>=1.6.0
Requires-Dist: numpy>=2.1.2
Requires-Dist: pillow>=12.0.0
Requires-Dist: requests>=2.32.3
Requires-Dist: typer>=0.19.1
Provides-Extra: dev
Requires-Dist: pytest; extra == 'dev'
Requires-Dist: pytest-cov>=5.0.0; extra == 'dev'
Requires-Dist: requests-mock>=1.12.1; extra == 'dev'
Requires-Dist: ruff; extra == 'dev'
Provides-Extra: docs
Requires-Dist: furo>=2024.8.6; extra == 'docs'
Requires-Dist: myst-nb>=1.1.2; extra == 'docs'
Requires-Dist: myst-parser>=4.0.0; extra == 'docs'
Requires-Dist: sphinx-copybutton>=0.5.2; extra == 'docs'
Requires-Dist: sphinx-inline-tabs>=2023.4.21; extra == 'docs'
Requires-Dist: sphinx>=8.0.2; extra == 'docs'
Requires-Dist: sphinxcontrib-typer[html]>=0.5.0; extra == 'docs'
Provides-Extra: full
Requires-Dist: matplotlib>=3.9.2; extra == 'full'
Provides-Extra: typed
Requires-Dist: mypy; extra == 'typed'
Requires-Dist: types-jsonschema; extra == 'typed'
Requires-Dist: types-requests; extra == 'typed'
